{
"instructions_readme": "1) Open Chrome, 2) go to chrome://tracing, 3) click Load, 4) navigate to this file.",

"traceEvents":[
{ "pid": 1, "tid": 1, "ph": "M", "name": "thread_name", "args": { "name": "" } },
{ "pid": 1, "tid": 1, "ts": 627.6, "dur": 8329152.8, "ph": "X", "name": "il2cpp.exe", "args": { "durationMS": 8329.1528, "detail": "" } },
{ "pid": 1, "tid": 1, "ts": 11042.7, "dur": 8318696, "ph": "X", "name": "ConvertAssemblies", "args": { "durationMS": 8318.696, "detail": "" } },
{ "pid": 1, "tid": 1, "ts": 30038.3, "dur": 82528.6, "ph": "X", "name": "Collect assemblies to convert", "args": { "durationMS": 82.5286, "detail": "" } },
{ "pid": 1, "tid": 1, "ts": 112884.2, "dur": 32174.4, "ph": "X", "name": "RegisterCorlib", "args": { "durationMS": 32.1744, "detail": "" } },
{ "pid": 1, "tid": 1, "ts": 145324.6, "dur": 33489.4, "ph": "X", "name": "PreProcessIL", "args": { "durationMS": 33.4894, "detail": "" } },
{ "pid": 1, "tid": 1, "ts": 145325.8, "dur": 7252, "ph": "X", "name": "Inject base types and finalizers into COM and Windows Runtime types", "args": { "durationMS": 7.252, "detail": "" } },
{ "pid": 1, "tid": 1, "ts": 145509.8, "dur": 6346, "ph": "X", "name": "ModifyCOMAndWindowsRuntimeTypes in assembly", "args": { "durationMS": 6.346, "detail": "mscorlib" } },
{ "pid": 1, "tid": 1, "ts": 152579.9, "dur": 26233.8, "ph": "X", "name": "ApplyDefaultMarshalAsAttribute", "args": { "durationMS": 26.2338, "detail": "" } },
{ "pid": 1, "tid": 1, "ts": 152712.8, "dur": 18603, "ph": "X", "name": "ApplyDefaultMarshalAsAttributeVisitor in assembly", "args": { "durationMS": 18.603, "detail": "mscorlib" } },
{ "pid": 1, "tid": 1, "ts": 171444.1, "dur": 666.9, "ph": "X", "name": "ApplyDefaultMarshalAsAttributeVisitor in assembly", "args": { "durationMS": 0.6669, "detail": "System" } },
{ "pid": 1, "tid": 1, "ts": 172229.1, "dur": 3546.7, "ph": "X", "name": "ApplyDefaultMarshalAsAttributeVisitor in assembly", "args": { "durationMS": 3.5467, "detail": "UnityEngine.SharedInternalsModule" } },
{ "pid": 1, "tid": 1, "ts": 175776.3, "dur": 1669, "ph": "X", "name": "ApplyDefaultMarshalAsAttributeVisitor in assembly", "args": { "durationMS": 1.669, "detail": "UnityEngine.CoreModule" } },
{ "pid": 1, "tid": 1, "ts": 177445.7, "dur": 354.1, "ph": "X", "name": "ApplyDefaultMarshalAsAttributeVisitor in assembly", "args": { "durationMS": 0.3541, "detail": "UnityEngine.AndroidJNIModule" } },
{ "pid": 1, "tid": 1, "ts": 178347.8, "dur": 406.2, "ph": "X", "name": "ApplyDefaultMarshalAsAttributeVisitor in assembly", "args": { "durationMS": 0.4062, "detail": "UnityEngine.IMGUIModule" } },
{ "pid": 1, "tid": 1, "ts": 178891.1, "dur": 9121, "ph": "X", "name": "WriteResources", "args": { "durationMS": 9.121, "detail": "" } },
{ "pid": 1, "tid": 1, "ts": 188119.2, "dur": 21551.7, "ph": "X", "name": "CopyEtcFolder", "args": { "durationMS": 21.5517, "detail": "" } },
{ "pid": 1, "tid": 1, "ts": 210443.5, "dur": 117474.6, "ph": "X", "name": "PreProcessStage", "args": { "durationMS": 117.4746, "detail": "" } },
{ "pid": 1, "tid": 1, "ts": 328571.5, "dur": 1226.7, "ph": "X", "name": "Debugger Sequence Points", "args": { "durationMS": 1.2267, "detail": "" } },
{ "pid": 1, "tid": 1, "ts": 330568.8, "dur": 483527.2, "ph": "X", "name": "Generics Collection", "args": { "durationMS": 483.5272, "detail": "" } },
{ "pid": 1, "tid": 1, "ts": 330569.9, "dur": 476073.5, "ph": "X", "name": "GenericsCollector.Collect", "args": { "durationMS": 476.0735, "detail": "" } },
{ "pid": 1, "tid": 1, "ts": 331213.2, "dur": 12042, "ph": "X", "name": "GenericCodeFlowGraphCollector.Collect", "args": { "durationMS": 12.042, "detail": "" } },
{ "pid": 1, "tid": 1, "ts": 331214.2, "dur": 11525.9, "ph": "X", "name": "GenericCodeFlowGraphCollector.GetTypesAndMethodsForAnalysis", "args": { "durationMS": 11.5259, "detail": "" } },
{ "pid": 1, "tid": 1, "ts": 806649.9, "dur": 6462.2, "ph": "X", "name": "CollectGenericVirtualMethods.Collect", "args": { "durationMS": 6.4622, "detail": "" } },
{ "pid": 1, "tid": 1, "ts": 813113.9, "dur": 783.5, "ph": "X", "name": "AddExtraTypes", "args": { "durationMS": 0.7835, "detail": "" } },
{ "pid": 1, "tid": 1, "ts": 814097.4, "dur": 818.2, "ph": "X", "name": "Add Windows Runtime type names", "args": { "durationMS": 0.8182, "detail": "" } },
{ "pid": 1, "tid": 1, "ts": 815720.4, "dur": 4542073.2, "ph": "X", "name": "AllAssemblyConversion", "args": { "durationMS": 4542.0732, "detail": "" } },
{ "pid": 1, "tid": 1, "ts": 816337.8, "dur": 3427508, "ph": "X", "name": "Convert assembly non-generic methods", "args": { "durationMS": 3427.508, "detail": "mscorlib" } },
{ "pid": 1, "tid": 1, "ts": 4243847.2, "dur": 3579, "ph": "X", "name": "Convert assembly non-generic methods", "args": { "durationMS": 3.579, "detail": "System.Configuration" } },
{ "pid": 1, "tid": 1, "ts": 4247427.2, "dur": 13354.1, "ph": "X", "name": "Convert assembly non-generic methods", "args": { "durationMS": 13.3541, "detail": "Mono.Security" } },
{ "pid": 1, "tid": 1, "ts": 4260783.2, "dur": 867.2, "ph": "X", "name": "Convert assembly non-generic methods", "args": { "durationMS": 0.8672, "detail": "System.Xml" } },
{ "pid": 1, "tid": 1, "ts": 4261651.6, "dur": 226194.6, "ph": "X", "name": "Convert assembly non-generic methods", "args": { "durationMS": 226.1946, "detail": "System" } },
{ "pid": 1, "tid": 1, "ts": 4487848, "dur": 1159.3, "ph": "X", "name": "Convert assembly non-generic methods", "args": { "durationMS": 1.1593, "detail": "System.Core" } },
{ "pid": 1, "tid": 1, "ts": 4489008.8, "dur": 15486.6, "ph": "X", "name": "Convert assembly non-generic methods", "args": { "durationMS": 15.4866, "detail": "UnityEngine.SharedInternalsModule" } },
{ "pid": 1, "tid": 1, "ts": 4504496.8, "dur": 373676.7, "ph": "X", "name": "Convert assembly non-generic methods", "args": { "durationMS": 373.6767, "detail": "UnityEngine.CoreModule" } },
{ "pid": 1, "tid": 1, "ts": 4878175.2, "dur": 88575.6, "ph": "X", "name": "Convert assembly non-generic methods", "args": { "durationMS": 88.5756, "detail": "UnityEngine.AndroidJNIModule" } },
{ "pid": 1, "tid": 1, "ts": 4966752, "dur": 2612.6, "ph": "X", "name": "Convert assembly non-generic methods", "args": { "durationMS": 2.6126, "detail": "UnityEngine.JSONSerializeModule" } },
{ "pid": 1, "tid": 1, "ts": 4969366, "dur": 37803, "ph": "X", "name": "Convert assembly non-generic methods", "args": { "durationMS": 37.803, "detail": "TDSCommon" } },
{ "pid": 1, "tid": 1, "ts": 5007171.2, "dur": 12720.2, "ph": "X", "name": "Convert assembly non-generic methods", "args": { "durationMS": 12.7202, "detail": "UnityEngine.InputLegacyModule" } },
{ "pid": 1, "tid": 1, "ts": 5019892.8, "dur": 2708.6, "ph": "X", "name": "Convert assembly non-generic methods", "args": { "durationMS": 2.7086, "detail": "UnityEngine.TextRenderingModule" } },
{ "pid": 1, "tid": 1, "ts": 5022603.2, "dur": 2434.8, "ph": "X", "name": "Convert assembly non-generic methods", "args": { "durationMS": 2.4348, "detail": "UnityNative.Toasts" } },
{ "pid": 1, "tid": 1, "ts": 5025039.2, "dur": 7268.9, "ph": "X", "name": "Convert assembly non-generic methods", "args": { "durationMS": 7.2689, "detail": "MS.NativeDialog" } },
{ "pid": 1, "tid": 1, "ts": 5032309.2, "dur": 4419.7, "ph": "X", "name": "Convert assembly non-generic methods", "args": { "durationMS": 4.4197, "detail": "TDSCore" } },
{ "pid": 1, "tid": 1, "ts": 5036730, "dur": 15209.3, "ph": "X", "name": "Convert assembly non-generic methods", "args": { "durationMS": 15.2093, "detail": "TDSLogin" } },
{ "pid": 1, "tid": 1, "ts": 5051941.2, "dur": 13445.7, "ph": "X", "name": "Convert assembly non-generic methods", "args": { "durationMS": 13.4457, "detail": "TDSMoment" } },
{ "pid": 1, "tid": 1, "ts": 5065388.4, "dur": 8802, "ph": "X", "name": "Convert assembly non-generic methods", "args": { "durationMS": 8.802, "detail": "TDSTapDB" } },
{ "pid": 1, "tid": 1, "ts": 5074192, "dur": 10831.8, "ph": "X", "name": "Convert assembly non-generic methods", "args": { "durationMS": 10.8318, "detail": "UnityEngine.AudioModule" } },
{ "pid": 1, "tid": 1, "ts": 5085026, "dur": 57004.1, "ph": "X", "name": "Convert assembly non-generic methods", "args": { "durationMS": 57.0041, "detail": "UnityEngine.GameCenterModule" } },
{ "pid": 1, "tid": 1, "ts": 5142031.6, "dur": 194712.3, "ph": "X", "name": "Convert assembly non-generic methods", "args": { "durationMS": 194.7123, "detail": "UnityEngine.IMGUIModule" } },
{ "pid": 1, "tid": 1, "ts": 5336746, "dur": 3384.8, "ph": "X", "name": "Convert assembly non-generic methods", "args": { "durationMS": 3.3848, "detail": "UnityNative.Toasts.Example" } },
{ "pid": 1, "tid": 1, "ts": 5340132, "dur": 362, "ph": "X", "name": "Convert assembly non-generic methods", "args": { "durationMS": 0.362, "detail": "UnityEngine" } },
{ "pid": 1, "tid": 1, "ts": 5340494.8, "dur": 17297.8, "ph": "X", "name": "Convert assembly non-generic methods", "args": { "durationMS": 17.2978, "detail": "Assembly-CSharp" } },
{ "pid": 1, "tid": 1, "ts": 5357944, "dur": 1449688.8, "ph": "X", "name": "WriteGenerics", "args": { "durationMS": 1449.6888, "detail": "" } },
{ "pid": 1, "tid": 1, "ts": 5359030, "dur": 412487.6, "ph": "X", "name": "GenericInstanceMethods", "args": { "durationMS": 412.4876, "detail": "" } },
{ "pid": 1, "tid": 1, "ts": 5771524.8, "dur": 922619.1, "ph": "X", "name": "GenericInstanceTypes", "args": { "durationMS": 922.6191, "detail": "" } },
{ "pid": 1, "tid": 1, "ts": 6694257.6, "dur": 113348.3, "ph": "X", "name": "GenericComDefinitions", "args": { "durationMS": 113.3483, "detail": "" } },
{ "pid": 1, "tid": 1, "ts": 6807831.2, "dur": 552.3, "ph": "X", "name": "Executable Processing", "args": { "durationMS": 0.5523, "detail": "" } },
{ "pid": 1, "tid": 1, "ts": 6808676.8, "dur": 197862.1, "ph": "X", "name": "MetadataCollector", "args": { "durationMS": 197.8621, "detail": "" } },
{ "pid": 1, "tid": 1, "ts": 6809827.2, "dur": 7098.9, "ph": "X", "name": "UpdateEmptyTokens", "args": { "durationMS": 7.0989, "detail": "" } },
{ "pid": 1, "tid": 1, "ts": 6817513.6, "dur": 7894.5, "ph": "X", "name": "ValidateTokens", "args": { "durationMS": 7.8945, "detail": "" } },
{ "pid": 1, "tid": 1, "ts": 7006974.4, "dur": 1806.8, "ph": "X", "name": "Write COM Callable Wrappers", "args": { "durationMS": 1.8068, "detail": "" } },
{ "pid": 1, "tid": 1, "ts": 7008868.8, "dur": 487.2, "ph": "X", "name": "Write Windows Runtime Factories", "args": { "durationMS": 0.4872, "detail": "" } },
{ "pid": 1, "tid": 1, "ts": 7009649.6, "dur": 1318639.5, "ph": "X", "name": "Metadata", "args": { "durationMS": 1318.6395, "detail": "Global" } },
{ "pid": 1, "tid": 1, "ts": 7038737.6, "dur": 496874.4, "ph": "X", "name": "Il2CppAttributes.cpp", "args": { "durationMS": 496.8744, "detail": "" } },
{ "pid": 1, "tid": 1, "ts": 7586564.8, "dur": 10768.1, "ph": "X", "name": "UnresolvedVirtualCallStubs.cpp", "args": { "durationMS": 10.7681, "detail": "" } },
{ "pid": 1, "tid": 1, "ts": 7598252, "dur": 199211.9, "ph": "X", "name": "WriteCodeRegistration", "args": { "durationMS": 199.2119, "detail": "" } },
{ "pid": 1, "tid": 1, "ts": 7598296, "dur": 74796.3, "ph": "X", "name": "mscorlib_CodeGen.c", "args": { "durationMS": 74.7963, "detail": "" } },
{ "pid": 1, "tid": 1, "ts": 7663437.6, "dur": 3323.9, "ph": "X", "name": "GenericContextCollector", "args": { "durationMS": 3.3239, "detail": "Collect" } },
{ "pid": 1, "tid": 1, "ts": 7673104.8, "dur": 576.3, "ph": "X", "name": "System.Configuration_CodeGen.c", "args": { "durationMS": 0.5763, "detail": "" } },
{ "pid": 1, "tid": 1, "ts": 7673689.6, "dur": 511.4, "ph": "X", "name": "Mono.Security_CodeGen.c", "args": { "durationMS": 0.5114, "detail": "" } },
{ "pid": 1, "tid": 1, "ts": 7674524.8, "dur": 2967.9, "ph": "X", "name": "System_CodeGen.c", "args": { "durationMS": 2.9679, "detail": "" } },
{ "pid": 1, "tid": 1, "ts": 7677501.6, "dur": 671.2, "ph": "X", "name": "System.Core_CodeGen.c", "args": { "durationMS": 0.6712, "detail": "" } },
{ "pid": 1, "tid": 1, "ts": 7678181.6, "dur": 781.6, "ph": "X", "name": "UnityEngine.SharedInternalsModule_CodeGen.c", "args": { "durationMS": 0.7816, "detail": "" } },
{ "pid": 1, "tid": 1, "ts": 7678971.2, "dur": 9375.9, "ph": "X", "name": "UnityEngine.CoreModule_CodeGen.c", "args": { "durationMS": 9.3759, "detail": "" } },
{ "pid": 1, "tid": 1, "ts": 7688359.2, "dur": 2137.8, "ph": "X", "name": "UnityEngine.AndroidJNIModule_CodeGen.c", "args": { "durationMS": 2.1378, "detail": "" } },
{ "pid": 1, "tid": 1, "ts": 7690506.4, "dur": 345.7, "ph": "X", "name": "UnityEngine.JSONSerializeModule_CodeGen.c", "args": { "durationMS": 0.3457, "detail": "" } },
{ "pid": 1, "tid": 1, "ts": 7690860.8, "dur": 869, "ph": "X", "name": "TDSCommon_CodeGen.c", "args": { "durationMS": 0.869, "detail": "" } },
{ "pid": 1, "tid": 1, "ts": 7691738.4, "dur": 484, "ph": "X", "name": "UnityEngine.InputLegacyModule_CodeGen.c", "args": { "durationMS": 0.484, "detail": "" } },
{ "pid": 1, "tid": 1, "ts": 7692231.2, "dur": 369.7, "ph": "X", "name": "UnityEngine.TextRenderingModule_CodeGen.c", "args": { "durationMS": 0.3697, "detail": "" } },
{ "pid": 1, "tid": 1, "ts": 7692609.6, "dur": 369.6, "ph": "X", "name": "UnityNative.Toasts_CodeGen.c", "args": { "durationMS": 0.3696, "detail": "" } },
{ "pid": 1, "tid": 1, "ts": 7692987.2, "dur": 358.7, "ph": "X", "name": "MS.NativeDialog_CodeGen.c", "args": { "durationMS": 0.3587, "detail": "" } },
{ "pid": 1, "tid": 1, "ts": 7693354.4, "dur": 343.9, "ph": "X", "name": "TDSCore_CodeGen.c", "args": { "durationMS": 0.3439, "detail": "" } },
{ "pid": 1, "tid": 1, "ts": 7693706.4, "dur": 650.9, "ph": "X", "name": "TDSLogin_CodeGen.c", "args": { "durationMS": 0.6509, "detail": "" } },
{ "pid": 1, "tid": 1, "ts": 7694367.2, "dur": 761.6, "ph": "X", "name": "TDSMoment_CodeGen.c", "args": { "durationMS": 0.7616, "detail": "" } },
{ "pid": 1, "tid": 1, "ts": 7695140.8, "dur": 675.2, "ph": "X", "name": "TDSTapDB_CodeGen.c", "args": { "durationMS": 0.6752, "detail": "" } },
{ "pid": 1, "tid": 1, "ts": 7695827.2, "dur": 969, "ph": "X", "name": "UnityEngine.AudioModule_CodeGen.c", "args": { "durationMS": 0.969, "detail": "" } },
{ "pid": 1, "tid": 1, "ts": 7696808.8, "dur": 2113.5, "ph": "X", "name": "UnityEngine.GameCenterModule_CodeGen.c", "args": { "durationMS": 2.1135, "detail": "" } },
{ "pid": 1, "tid": 1, "ts": 7698942.4, "dur": 5065.7, "ph": "X", "name": "UnityEngine.IMGUIModule_CodeGen.c", "args": { "durationMS": 5.0657, "detail": "" } },
{ "pid": 1, "tid": 1, "ts": 7704030.4, "dur": 472.6, "ph": "X", "name": "UnityNative.Toasts.Example_CodeGen.c", "args": { "durationMS": 0.4726, "detail": "" } },
{ "pid": 1, "tid": 1, "ts": 7704802.4, "dur": 617.6, "ph": "X", "name": "Assembly-CSharp_CodeGen.c", "args": { "durationMS": 0.6176, "detail": "" } },
{ "pid": 1, "tid": 1, "ts": 7706048, "dur": 770.8, "ph": "X", "name": "Il2CppReversePInvokeWrapperTable.cpp", "args": { "durationMS": 0.7708, "detail": "" } },
{ "pid": 1, "tid": 1, "ts": 7706953.6, "dur": 35894, "ph": "X", "name": "Il2CppGenericMethodPointerTable.cpp", "args": { "durationMS": 35.894, "detail": "" } },
{ "pid": 1, "tid": 1, "ts": 7743105.6, "dur": 42171.3, "ph": "X", "name": "Il2CppInvokerTable.cpp", "args": { "durationMS": 42.1713, "detail": "" } },
{ "pid": 1, "tid": 1, "ts": 7785796, "dur": 9521.1, "ph": "X", "name": "Il2CppInteropDataTable.cpp", "args": { "durationMS": 9.5211, "detail": "" } },
{ "pid": 1, "tid": 1, "ts": 7796742.4, "dur": 721.6, "ph": "X", "name": "Il2CppCodeRegistration.cpp", "args": { "durationMS": 0.7216, "detail": "" } },
{ "pid": 1, "tid": 1, "ts": 7797468, "dur": 530820.4, "ph": "X", "name": "WriteMetadata", "args": { "durationMS": 530.8204, "detail": "" } },
{ "pid": 1, "tid": 1, "ts": 7802432.8, "dur": 112226.5, "ph": "X", "name": "Il2CppMetadataUsage.c", "args": { "durationMS": 112.2265, "detail": "" } },
{ "pid": 1, "tid": 1, "ts": 7848627.2, "dur": 2704.5, "ph": "X", "name": "Metadata", "args": { "durationMS": 2.7045, "detail": "Collect string literals" } },
{ "pid": 1, "tid": 1, "ts": 7922996, "dur": 12740.7, "ph": "X", "name": "Il2CppGenericClassTable.c", "args": { "durationMS": 12.7407, "detail": "" } },
{ "pid": 1, "tid": 1, "ts": 7935750.4, "dur": 15498.6, "ph": "X", "name": "Il2CppGenericInstDefinitions.c", "args": { "durationMS": 15.4986, "detail": "" } },
{ "pid": 1, "tid": 1, "ts": 7951263.2, "dur": 92405.2, "ph": "X", "name": "Il2CppGenericMethodTable.c", "args": { "durationMS": 92.4052, "detail": "" } },
{ "pid": 1, "tid": 1, "ts": 8043682.4, "dur": 54316.9, "ph": "X", "name": "Il2CppTypeDefinitions.c", "args": { "durationMS": 54.3169, "detail": "" } },
{ "pid": 1, "tid": 1, "ts": 8098014.4, "dur": 23400.2, "ph": "X", "name": "Il2CppGenericMethodDefinitions.c", "args": { "durationMS": 23.4002, "detail": "" } },
{ "pid": 1, "tid": 1, "ts": 8121420.8, "dur": 79310.5, "ph": "X", "name": "CompilerCalculateTypeValues", "args": { "durationMS": 79.3105, "detail": "" } },
{ "pid": 1, "tid": 1, "ts": 8200750.4, "dur": 1640.3, "ph": "X", "name": "Il2CppMetadataRegistration.c", "args": { "durationMS": 1.6403, "detail": "" } },
{ "pid": 1, "tid": 1, "ts": 8202774.4, "dur": 5870.5, "ph": "X", "name": "StringLiteralWriter", "args": { "durationMS": 5.8705, "detail": "" } },
{ "pid": 1, "tid": 1, "ts": 8208753.6, "dur": 788.6, "ph": "X", "name": "Metadata Strings", "args": { "durationMS": 0.7886, "detail": "" } },
{ "pid": 1, "tid": 1, "ts": 8209545.6, "dur": 3583.9, "ph": "X", "name": "Events", "args": { "durationMS": 3.5839, "detail": "" } },
{ "pid": 1, "tid": 1, "ts": 8213133.6, "dur": 5515, "ph": "X", "name": "Properties", "args": { "durationMS": 5.515, "detail": "" } },
{ "pid": 1, "tid": 1, "ts": 8218655.2, "dur": 30903.4, "ph": "X", "name": "Methods", "args": { "durationMS": 30.9034, "detail": "" } },
{ "pid": 1, "tid": 1, "ts": 8249568.8, "dur": 3183.9, "ph": "X", "name": "Parameter Default Values", "args": { "durationMS": 3.1839, "detail": "" } },
{ "pid": 1, "tid": 1, "ts": 8252756.8, "dur": 3736.8, "ph": "X", "name": "Field Default Values", "args": { "durationMS": 3.7368, "detail": "" } },
{ "pid": 1, "tid": 1, "ts": 8256497.6, "dur": 527.1, "ph": "X", "name": "Field and Parameter Default Values Data", "args": { "durationMS": 0.5271, "detail": "" } },
{ "pid": 1, "tid": 1, "ts": 8257029.6, "dur": 384.5, "ph": "X", "name": "Field Marshaled Sizes", "args": { "durationMS": 0.3845, "detail": "" } },
{ "pid": 1, "tid": 1, "ts": 8257417.6, "dur": 8902.4, "ph": "X", "name": "Parameters", "args": { "durationMS": 8.9024, "detail": "" } },
{ "pid": 1, "tid": 1, "ts": 8266325.6, "dur": 6457.8, "ph": "X", "name": "Fields", "args": { "durationMS": 6.4578, "detail": "" } },
{ "pid": 1, "tid": 1, "ts": 8272788, "dur": 3307.2, "ph": "X", "name": "Generic Parameters", "args": { "durationMS": 3.3072, "detail": "" } },
{ "pid": 1, "tid": 1, "ts": 8276099.2, "dur": 750.8, "ph": "X", "name": "Generic Parameter Constraints", "args": { "durationMS": 0.7508, "detail": "" } },
{ "pid": 1, "tid": 1, "ts": 8276855.2, "dur": 3230.2, "ph": "X", "name": "Generic Containers", "args": { "durationMS": 3.2302, "detail": "" } },
{ "pid": 1, "tid": 1, "ts": 8280499.2, "dur": 1595.1, "ph": "X", "name": "VTables", "args": { "durationMS": 1.5951, "detail": "" } },
{ "pid": 1, "tid": 1, "ts": 8282099.2, "dur": 1134, "ph": "X", "name": "Interface Offsets", "args": { "durationMS": 1.134, "detail": "" } },
{ "pid": 1, "tid": 1, "ts": 8283237.6, "dur": 26977.7, "ph": "X", "name": "Type Definitions", "args": { "durationMS": 26.9777, "detail": "" } },
{ "pid": 1, "tid": 1, "ts": 8310227.2, "dur": 4769.9, "ph": "X", "name": "Images", "args": { "durationMS": 4.7699, "detail": "" } },
{ "pid": 1, "tid": 1, "ts": 8315002.4, "dur": 3404.4, "ph": "X", "name": "Assemblies", "args": { "durationMS": 3.4044, "detail": "" } },
{ "pid": 1, "tid": 1, "ts": 8318410.4, "dur": 614.2, "ph": "X", "name": "Metadata Usage Lists", "args": { "durationMS": 0.6142, "detail": "" } },
{ "pid": 1, "tid": 1, "ts": 8319028.8, "dur": 1572.1, "ph": "X", "name": "Metadata Usage Pairs", "args": { "durationMS": 1.5721, "detail": "" } },
{ "pid": 1, "tid": 1, "ts": 8320703.2, "dur": 446.3, "ph": "X", "name": "Referenced Assemblies", "args": { "durationMS": 0.4463, "detail": "" } },
{ "pid": 1, "tid": 1, "ts": 8321153.6, "dur": 1545.5, "ph": "X", "name": "Attribute Types Ranges", "args": { "durationMS": 1.5455, "detail": "" } },
{ "pid": 1, "tid": 1, "ts": 8323126.4, "dur": 503.3, "ph": "X", "name": "Unresolved Virtual Call Parameter Ranges", "args": { "durationMS": 0.5033, "detail": "" } },
{ "pid": 1, "tid": 1, "ts": 8323773.6, "dur": 3543.1, "ph": "X", "name": "Exported Types", "args": { "durationMS": 3.5431, "detail": "" } },
{ "pid": 1, "tid": 1, "ts": 8328443.2, "dur": 676, "ph": "X", "name": "CompletionPhase", "args": { "durationMS": 0.676, "detail": "" } }
],
"meta_datetime": "12/29/2020 11:32:00",
"meta_command_line": "/Applications/Unity/Hub/Editor/2020.1.17f1c1/Unity.app/Contents/il2cpp/build/deploy/net471/il2cpp.exe --convert-to-cpp --emit-null-checks --enable-array-bounds-check --dotnetprofile=unityaot --incremental-g-c-time-slice=3 --avoid-dynamic-library-copy --profiler-report --map-file-parser=/Applications/Unity/Hub/Editor/2020.1.17f1c1/Unity.app/Contents/Tools/MapFileParser/MapFileParser --directory=/Users/taptap-david/Desktop/TapSDK_Unity_Demo/Temp/StagingArea/Data/Managed --generatedcppdir=/Users/taptap-david/Desktop/TapSDK_Unity_Demo/Temp/il2cppOutput/il2cppOutput",
"meta_command_line_args": "/Applications/Unity/Hub/Editor/2020.1.17f1c1/Unity.app/Contents/il2cpp/build/deploy/net471/il2cpp.exe --convert-to-cpp --emit-null-checks --enable-array-bounds-check --dotnetprofile=unityaot --incremental-g-c-time-slice=3 --avoid-dynamic-library-copy --profiler-report --map-file-parser=/Applications/Unity/Hub/Editor/2020.1.17f1c1/Unity.app/Contents/Tools/MapFileParser/MapFileParser --directory=/Users/taptap-david/Desktop/TapSDK_Unity_Demo/Temp/StagingArea/Data/Managed --generatedcppdir=/Users/taptap-david/Desktop/TapSDK_Unity_Demo/Temp/il2cppOutput/il2cppOutput",
"meta_user_name": "taptap-david",
"meta_os_version": "Unix 19.5.0.0",
"meta_cpu_count": "16"}
